setup.cfg
setup.py
behave_api_utils/__init__.py
behave_api_utils/api_services.py
behave_api_utils/rest.py
behave_api_utils.egg-info/PKG-INFO
behave_api_utils.egg-info/SOURCES.txt
behave_api_utils.egg-info/dependency_links.txt
behave_api_utils.egg-info/requires.txt
behave_api_utils.egg-info/top_level.txt