Metadata-Version: 1.1
Name: behave-api-utils
Version: 1.2.0
Summary: API Services utils library to use with Behave projects
Home-page: https://github.com/borbamartin/behave-api-utils
Author: Martin Borba
Author-email: borbamartin@gmail.com
License: UNKNOWN
Download-URL: https://github.com/borbamartin/behave-api-utils/tarball/1.2.0
Keywords: api,rest,services
Platform: UNKNOWN
